{
    "11 Mai 2018": [
        "Daniel",
        "Albino da",
        "Nuno",
        "Cândida Teixeira",
        "Paula Silva",
        "Conceição",
        "Esperança",
        "Albino da Conceição",
        "Maria Cândida",
        "David Bernardino",
        "João Ernesto",
        "Ernesto dos Santos",
        "Margarida"
    ],
    "29 Abr 2018": [
        "Lúcio",
        "Filomena Wilson",
        "Eduardo",
        "Eduardo Alves",
        "Arlete",
        "António Capitão",
        "Catarina Domingos",
        "Gabriel",
        "António Cristóvão",
        "Esperança",
        "Hilário",
        "Tomé",
        "Alberto",
        "António Carmina",
        "Josué Gaspar",
        "Rui",
        "Lourenço António",
        "Angela",
        "Branca",
        "Hamilton",
        "Mercedes",
        "Daniel",
        "Maria"
    ],
    "30 Abr 2018": [
        "Mara",
        "Maria",
        "Domingos",
        "António Gonçalo",
        "João Bernardo",
        "Alfredo Ferreira",
        "Jorge",
        "Luís Figueiredo",
        "Leandro",
        "Jofre",
        "Jofre dos Santos",
        "Pedro",
        "Dilma",
        "Pedro dos Santos",
        "Isaac",
        "Esperança",
        "Paulo Torres",
        "Geraldo",
        "Valério",
        "António Lopes",
        "Juliana Domingos",
        "José Gomes",
        "Esperança",
        "Domingos",
        "José Carvalho",
        "Domingos do Nascimento",
        "André da Costa",
        "André da",
        "Victor"
    ],
    "27 Abr 2018": [
        "Luís Bagorro",
        "Margarida",
        "João Lourenço",
        "António Paulo",
        "Eduardo dos Santos",
        "Agostinho Neto",
        "José Eduardo",
        "António Agostinho",
        "Teodoro",
        "Diogo Paixão",
        "Liliana",
        "Purificação",
        "Manuel"
    ],
    "24 Abr 2018": [
        "José Mena",
        "Pedro Gomes",
        "José",
        "Telma Anair",
        "Abel Jones",
        "Ricardo",
        "Anair Mana",
        "Nina",
        "André",
        "América"
    ],
    "23 Abr 2018": [
        "Bernard",
        "Anabela",
        "António Egídio",
        "João Lourenço",
        "Egídio de Sousa",
        "Benedito",
        "Adriano Mendes",
        "Narciso Damásio",
        "América"
    ],
    "03 Mai 2018": [
        "Paulo",
        "Laurinda",
        "Paulo de Carvalho",
        "Agostinho Neto",
        "José Celestino",
        "Celestino da Silva",
        "Celestino da",
        "IVA",
        "IVA da",
        "Adilson Sequeira",
        "Henrique",
        "Alberto Pinto",
        "Carlos Alberto",
        "João Lourenço",
        "Edgar",
        "Manuel Augusto",
        "Ângelo da Veiga",
        "Ângelo da",
        "Marcos",
        "Adelino de Almeida",
        "Adelino",
        "Luísa Rogério",
        "Francisco",
        "Pedro"
    ],
    "28 Abr 2018": [
        "Justino Vitorino",
        "José Chaves",
        "Aristides Gonçalves",
        "Luísa Victorino",
        "Sebastião",
        "Domingos Eduardo",
        "Francisco Alexandre",
        "Joana Costa",
        "Juliana Machado",
        "Teresa Almeida",
        "Cristina Branco",
        "Eduardo",
        "Liliana Venâncio",
        "Magda",
        "Eliane Mota",
        "Albertina",
        "Luísa",
        "Francisco",
        "Francisco de Almeida",
        "Dalva Peres",
        "Isabel",
        "Natália Bernardo",
        "Carolina Morais",
        "Suzete",
        "Filomena Wilson",
        "Manuel Fontoura",
        "José",
        "João Lourenço",
        "José de Almeida",
        "Ana Graça"
    ],
    "25 Abr 2018": [
        "Ernesto",
        "Pedro Gomes",
        "Manuel Queiroz",
        "Francisco",
        "Filomena Bento",
        "Augusto Miranda",
        "Francisco Damião",
        "Pedro Gomes",
        "José Mena",
        "Telma Anair",
        "Abel Jones",
        "Anair Mana",
        "Raimundo Ricardo",
        "António Fonseca",
        "Carlos Ferreira",
        "Dario",
        "António Jacinto",
        "Adão",
        "Irene Marques",
        "Dario de Melo",
        "Luís Sampaio",
        "David",
        "Steven"
    ],
    "26 Abr 2018": [
        "Félix Belarmino",
        "Domingos Moreira",
        "Gaspar",
        "Tony Morgado",
        "Arnaldo Macedo",
        "Paulino da",
        "Agostinho Neto",
        "Gabriel",
        "Hilário Ventura",
        "Céu",
        "Micael Daniel",
        "Clementina",
        "Joaquim Manuel",
        "Carlos Vicente",
        "Tomé",
        "América",
        "Eduardo",
        "Ivan",
        "Valter Costa",
        "Mauro",
        "Alexandre Costa",
        "Mara",
        "Carlos Gregório",
        "Telma Lee",
        "José",
        "José Afonso",
        "João Oliveira",
        "Roger",
        "Jerónimo Belo",
        "Fernando",
        "Teresa"
    ],
    "04 Mai 2018": [
        "Afonso",
        "Filipe",
        "Domingos Cardoso",
        "Agostinho Domingos",
        "Joyce",
        "Peter",
        "Eduardo Paim",
        "Ernesto",
        "Tomás",
        "António Agostinho",
        "Agostinho Neto",
        "Maria",
        "Jesus",
        "Maria de Jesus"
    ],
    "21 Abr 2018": [
        "Domingos Pedro",
        "Juliana Domingos",
        "Mara",
        "José",
        "Albano Machado",
        "Urbano",
        "Norberto dos Santos",
        "Pedro Luís",
        "Benedito Roberto",
        "Augusta da Silva",
        "Augusta da",
        "Tomás",
        "Augusto Tomás",
        "Maria",
        "Fernanda",
        "Urbano",
        "Eduardo Cerqueira",
        "Manuela Maria",
        "João Lourenço",
        "Maria da",
        "Antónia",
        "Pedro Neves",
        "Eurídice Contreiras",
        "Adriano Mendes",
        "António Fiel",
        "António Antas",
        "Ana Eurídice",
        "Agostinho Pedro",
        "Conceição de Carvalho",
        "Conceição Bezerra",
        "Conceição",
        "Maria da Conceição",
        "Jeremias",
        "André",
        "Miguel",
        "Pedro",
        "Sebastião António"
    ]
}