<?xml version="1.0" encoding="UTF-8"?>
<xml>
<Date>
27 Abr 2018 / 16:02
	  	  
 H.
</Date>
<Sec>
Geral
</Sec>
<Title>
Leonardo Jardim entre os nomeados para melhor treinador do ano
</Title>
<Text>
Os portugueses Leonardo Jardim, treinador do Mónaco, e Anthony Lopes, guarda-redes do Lyon, estão nomeados para os ‘Troféus do Futebol, que premeiam anualmente os melhores da liga francesa de futebol a cada época.
O treinador Leonardo Jardim está nomeado, pela segunda vez consecutiva, para o prémio de melhor treinador, depois de ter vencido no ano passado, o mesmo ano em que se sagrou campeão francês pelo Mónaco.
Os concorrentes do treinador português são Olivier Dall’Oglio (Dijon), Unai Emery (Paris Saint-Germain) e Rudi Garcia (Marselha).
O internacional Anthony Lopes está nomeado pela quarta vez para melhor guarda-redes da ‘Ligue 1’, distinção que nunca obteve, e cujo prémio na época passada foi atribuído a Danijel Subasic, guarda-redes do Mónaco.
Anthony Lopes, que é campeão europeu pela selecção portuguesa, embora fosse suplente no Euro2016, tem como adversários Steve Mandanda (Marselha), Alphonse Areola (Paris Saint-Germain) e Benjamin Lecomte (Montpellier).
A cerimónia de entrega de prémios está agendada para 13 de Maio.
</Text>
<Autor>
Agência Lusa
</Autor>
</xml>