<?xml version="1.0" encoding="UTF-8"?><xml>
<Date>
25 Mai 2018 / 10:16
	  	  
 H.
</Date>
<Sec>
Geral
</Sec>
<Title>
Carrinha saiu de estrada e foi parar a um terreno de vinha em Santana
</Title>
<Text>
Uma carrinha de nove lugares despistou-se ontem à noite em Santana, na subida para a Ilha, e saiu de estrada, caindo de uma altura aproximada a 20 metros para um terreno de vinha.
Na viatura seguiam três homens, o condutor, de 32 anos, e mais dois rapazes de 19 anos, que sofreram ferimentos na sequência do acidente.
O alerta foi dado aos Bombeiros Voluntários de Santana, às 22h20, que se deslocaram ao local para prestar socorro às vítimas. Os sinistrados foram imobilizados e transportados de ambulância para o Centro de Saúde de Machico.
Após uma avaliação médica um deles teve alta e os outros dois foram encaminhados para o Hospital Dr. Nélio Mendonça.
A Polícia de Segurança Pública também esteve presente e tomou conta da ocorrência.
</Text>
<Autor>
Andreína Ferreira
</Autor></xml>
