<?xml version="1.0" encoding="UTF-8"?><xml>
<Date>
26 Mai 2018 / 21:36
	  	  
 H.
</Date>
<Sec>
Geral
</Sec>
<Title>
‘Aleste’ é que se está bem, veja as fotos do festival deste sábado na Ponta Gorda
</Title>
<Text>
O Festival Aleste voltou a conquistar muito público para aquele que é considerado um dos eventos mais badalados da Região.
Este ano, o festival está a decorrer no Complexo Balnear da Ponta Gorda, no Funchal, sendo que os dinamarqueses Laid Back são um dos grandes destaques.
</Text>
<Autor>
Fotos Rui Silva/ASPRESS
Sandra da Silva Gonçalves
</Autor></xml>
