<?xml version="1.0" encoding="UTF-8"?><xml>
<Date>
08 Jun 2018 / 18:26
	  	  
 H.
</Date>
<Sec>
Geral
</Sec>
<Title>
Trabalhadores da Empresa de Cervejas da Madeira com aumento salarial de 2,5%
</Title>
<Text>
Decorreu ontem, 7 de Junho, a assinatura do Acordo de Empresa entre a Empresa de Cervejas da Madeira e os representantes da Federação dos Sindicatos da Agricultura, Alimentação, Bebidas, Hotelaria Turismo de Portugal e do Sindicato dos Trabalhadores Rodoviários e Actividades Metalúrgicas da RAM.
Trata-se do culminar de um longo processo negocial, entre as partes, iniciado em 2013 e acompanhado pela DRTAI, tendo presente que a última tabela salarial datava de Dezembro de 2011 e perante a qual existia uma proposta de revisão datada de Dezembro de 2012.
Na globalidade, o Acordo de Empresa agora alcançado prevê um aumento na Tabela Salarial de 2,5% e aumentos relevantes nas cláusulas de expressão pecuniária (diuturnidades, subsidio de alimentação, abono para falhas, e outros) para um universo de 233 trabalhadores, assim como uma remuneração mínima de 605 euros, no âmbito da Empresa. Estes aumentos produzem efeitos a partir de 01 de maio do presente ano.
Assiste ao ato de assinatura do Acordo de Empresa o Director Regional do Trabalho e da Acção Inspectiva.
</Text>
<Autor>
</Autor></xml>
