<?xml version="1.0" encoding="UTF-8"?><xml>
<Date>
10 Jun 2018 / 15:37
	  	  
 H.
</Date>
<Sec>
Geral
</Sec>
<Title>
Atletas madeirenses ganham medalha de bronze em campeonato de Judo
</Title>
<Text>
A Madeira participou no Campeonato Nacional de Juvenis e no Campeonato Nacional de Equipas de Cadetes, em Odivelas, provas organizadas pela Federação Portuguesa de Judo.
Nos Juvenis, a Região esteve representada pelo Clube Naval do Funchal e pelo Judo Clube da Madeira, num total de 6 atletas, tendo estes sido vencidos apenas pela sua inexperiência nos tapetes nacionais.
Já nas equipas cadetes, o Judo Clube da Madeira apresentou uma equipa de atletas experientes e já medalhadas em Campeonatos Nacionais. Beatriz Caires nos -52Kg, Leonor Gomes nos -57Kg, Beatriz Rocha nos -63Kg e Fátima Andrade nos +63Kg, acabaram esta prova de Bronze ao peito, tendo apenas sucumbido nas meias finais frente à equipa que havia de se sagrar campeã nacional, do Sporting Clube Portugal.
</Text>
<Autor>
</Autor></xml>
