<?xml version="1.0" encoding="UTF-8"?>

<xml>
<Date>
Fri, 25 Nov 2016 23:06:58 GMT
</Date>
<Sec>
Geral
</Sec><Title>
Euromilhões dividido por dois apostadores no estrangeiro
</Title>
<Text>


O primeiro prémio do concurso de hoje do Euromilhões, no valor de 60 milhões de euros, vai ser distribuído por dois apostadores no estrangeiro, informou a Santa Casa da Misericórdia de Lisboa.

O segundo prémio vai ser distribuído por seis apostadores, também no estrangeiro, que vão receber, cada um, cerca de 209 mil euros.

Com o terceiro prémio foram apurados 33 apostadores, seis dos quais em Portugal, que vão receber, cada um, cerca de 8.800 euros.

O quarto prémio vai ser distribuído por 49 apostadores, 12 dos quais em Portugal, cabendo a, cada um, cerca de 2.900 euros.

A combinação vencedora do concurso 95/2016 do Euromilhões, sorteada hoje, é composta pelos números 05 - 11 - 17 - 23 -- 28 e pelas estrelas 10 e 11. 

</Text>
</xml>
