<?xml version="1.0" encoding="UTF-8"?>

<xml>
<Date>
Tue, 25 Oct 2016 10:00:48 GMT
</Date>
<Sec>
Geral
</Sec><Title>
 Polícia já localizou homem que fugiu do tribunal na Madeira
</Title>
<Text>


O homem de 30 anos que tinha sido detido por furto a um estabelecimento e que fugiu do Tribunal Judicial do Funchal no final do dia de ontem, já foi localizado pela Polícia de Segurança Pública e está neste momento no Comando Regional da PSP.



O DIÁRIO apurou, em informação de última hora, que o suspeito acabou por ser localizado na freguesia da Quinta Grande, concelho de Câmara de Lobos, nas imediações da casa onde vive. 



O suspeito, com antecedentes criminais, encontrava-se em parte incerta desde o final do dia de ontem. Desde então a PSP desencadeou uma operação de buscas com um alerta geral pelas várias esquadras. 



Recorde-se que o arguido encontrava-se com outros três indivíduos implicados num assalto perpetrado num estabelecimento do concelho do Porto Moniz quando conseguiu escapar do Tribunal Judicial do Funchal.

</Text>
</xml>
