<?xml version="1.0" encoding="UTF-8"?>

<xml>
<Date>
Sat, 29 Oct 2016 16:06:09 GMT
</Date>
<Sec>
Geral
</Sec><Title>
Idoso encontrado morto em Agualva-Cacém (Sintra), numa casa com sinais de assalto
</Title>
<Text>


Um homem de 82 anos foi hoje encontrado morto na freguesia de Agualva-Cacém, no concelho de Sintra, no interior da casa onde residia e que apresentava sinais de ter sido assaltada, informou fonte dos bombeiros de Agualva-Cacém.

De acordo com o Comando Distrital de Operações de Socorro (CDOS), os meios foram chamados às 13:30 para um socorro com uma vítima mortal.

Fonte dos Bombeiros de Agualva-Cacém salientou que os bombeiros foram chamados para socorrer um homem de 82 anos encontrado morto na sua residência.

Quando os bombeiros chegaram ao local, depararam com “a vítima já cadáver com alguma rigidez” e encontraram “a casa remexida, pelo que suspeitaram de assalto e chamaram a PSP”, acrescentou.

No local, estiveram uma ambulância dos Bombeiros de Agualva-Cacém, uma viatura médica do INEM, assim como elementos da PSP e da Polícia Judiciária.

</Text>
</xml>
