<?xml version="1.0" encoding="UTF-8"?>

<xml>
<Date>
Fri, 30 Dec 2016 10:13:57 GMT
</Date>
<Sec>
Geral
</Sec><Title>
Várias viaturas vandalizadas no Funchal
</Title>
<Text>


Vários automóveis foram danificados nas últimas duas noites, no Funchal, em actos de vandalismo cuja autoria é desconhecida.

Segundo o DIÁRIO apurou, os veículos vandalizados encontravam-se estacionados entre a Rua Imperatriz Dona Amélia, Penha de França e o Museu Cristiano Ronaldo.

Os autores do crime chegaram mesmo a partir alguns vidros das viaturas e furtaram alguns bens que se encontravam no seu interior.

</Text>
</xml>
