<?xml version="1.0" encoding="UTF-8"?>

<xml>
<Date>
Mon, 28 Nov 2016 21:12:47 GMT
</Date>
<Sec>
Geral
</Sec><Title>
Albuquerque reuniu-se com militantes do Monte
</Title>
<Text>


O presidente do PSD-M reuniu-se hoje com os militantes do Monte. Miguel Albuquerque mostrou-se satisfeito com a participação nas reuniões realizadas em todos os concelhos e nas freguesias do Funchal.

O líder do PSD-M considera que os militantes “estão preparados” para o próximo congresso que, afirma,  marcará o início de “um novo ciclo” político de reconquista da maioria das câmaras da Região.

“Temos todas as condições para disputar a liderança da maioria das câmaras, temos óptimos quadros, sempre fomos um partido de base autárquica, dado a matriz eminentemente popular do PSD e a sua proximidade à população”, afirmou.

Amanhã, o encontro com os militantes decorre em São Roque, fechando esta segunda ronda de reuniões com as bases do partido.

</Text>
</xml>
