<?xml version="1.0" encoding="UTF-8"?>

<xml>
<Date>
Fri, 25 Nov 2016 08:08:53 GMT
</Date>
<Sec>
Geral
</Sec><Title>
Chuva até meio da manhã
</Title>
<Text>


Instituto Português do Mar e da Atmosfera prevê períodos de céu muito nublado, apresentando-se geralmente muito nublado até final da manhã. Haverá períodos de chuva ou aguaceiros, por vezes fortes até meio da manhã e condições favoráveis à ocorrência de trovoada.

O vento será moderado a forte (30 a 45 km/h) do quadrante Oeste, tornando-se do quadrante Norte a partir do final da manhã.

Para o Funchal, o IPMA prevê períodos de céu muito nublado, períodos de chuva ou aguaceiros até final da manhã com possibilidade de ocorrência de trovoada e vento fraco (inferior a 15 km/h), soprando temporariamente moderado (15 a 30 km/h) de Sudoeste até meio da manhã.

O aviso amarelo para precipitação mantém-se até às 10 horas de hoje na Costa Sul e no Porto Santo, sendo laranja nas regiões montanhosas.

Quanto ao estado do mar, na Costa Norte as ondas serão de Noroeste com 2 a 2,5 metros e na Costa Sul de sudoeste com 1 a 1,5 metros. A temperatura da água do mar vai estar entre os 20 e 21ºC.

</Text>
</xml>
