<?xml version="1.0" encoding="UTF-8"?>

<xml>
<Date>
Mon, 28 Nov 2016 16:57:14 GMT
</Date>
<Sec>
Geral
</Sec><Title>
Detido com quatro quilos de cocaína no aeroporto
</Title>
<Text>


Um angolano foi detido no sábado no Aeroporto Internacional de São Paulo em Guarulhos, no Brasil, “com quase quatro quilos de cocaína escondidos em sete pares de chinelos”, informou hoje a Polícia Federal. 

“O homem, de 27 anos, já havia despachado as suas malas, mas os polícias identificaram a droga com o auxílio do ‘raio-x’ no porão de bagagens. Ele foi localizado e preso na sala de embarque”, lê-se numa nota daquela força de segurança.

No total, de sexta-feira a domingo, a Polícia Federal apreendeu naquele aeroporto 19 quilos de drogas com passageiros de voos internacionais. 

Os restantes detidos são da Venezuela, África do Sul, Holanda, Zimbabué e Filipinas.

Os presos foram conduzidos a cadeias estaduais, sendo a pena para o crime de tráfico internacional de drogas de cinco a 15 anos de prisão.

</Text>
</xml>
