<?xml version="1.0" encoding="UTF-8"?><xml>
<Date>
25.05.2018 às 18h00
</Date>
<Sec>
Cartas a um conhecido
</Sec>
<Title>
Expresso | Carta a Pedro Siza Vieira
</Title>
<Description>
Carta de desculpa a Pedro Siza Vieira
</Description>
<Text>
Exmo.Senhor Ministro Adjunto  Pedro Siza Vieira  Rua Professor Gomes Teixeira, 2 - 1399-022 Lisboa   Espero que esta o encontre bem, e espero também que não me leve a mal. Caso não tivesse acontecido esta confusão toda dos chineses e da empresa de imóveis ou de gestão de condomínios, na mesma semana em que o António Costa andou nas bocas do mundo por ter comprado e vendido uma casa pelo dobro, se não fosse por isto tudo, e a sério, não fique zangado, nem me lembrava da sua existência. Para continuar a ler o artigo, clique AQUI (acesso gratuito: basta usar o código que está na capa da revista E do Expresso. pode usar a app do Expresso - iOS e android - para fotografar o código e o acesso será logo concedido)
</Text></xml>
