<?xml version="1.0" encoding="UTF-8"?><xml>
<Date>
Quarta, 25 de Abril 2018 12:57
</Date>
<Sec>
Províncias
</Sec>
<Title>
Sector da Educação tem novo director
</Title>
<Text>
Raimundo Ricardo é o novo director provincial da Educação, Ciências e Tecnologia no Moxico, em substituição de Abel Jones Pique. O sector da Educação era o único que ainda não tinha director e, durante cinco meses, foi dirigido pela chefe de Departamento de Administração e Finanças, Telma Anair Mana.
Raimundo Ricardo prometeu, no acto de apresentação aos seus mais directos colaboradores e professores de diferentes subsistemas de ensino, trabalhar para dar solução aos problemas que afligem o sector e a classe de professores no Moxico.
O encontro de apresentação permitiu ao novo director conhecer os principais problemas que preocupam os docentes da província, que passam pela normalização dos processos da segurança social, vandalismo nas escolas, reconversão de carreiras e a falta de professores de educação física. A lista de preocupações dos professores inclui a falta de acções formativas. 
</Text>
<Autor>
José Rufino
</Autor>
</xml>
