<?xml version="1.0" encoding="UTF-8"?><xml>
<Date>
Segunda, 21 de Maio 2018 09:54
</Date>
<Sec>
Mundo
</Sec>
<Title>
China e Estados Unidos selam acordo comercial
</Title>
<Text>

20 de Maio, 2018

A China e os Estados Unidos decidiram renunciar a qualquer guerra  comercial e à imposição de novas taxas aduaneiras entre os dois países,  afirmou ontem o vice-primeiro-ministro chinês, Liu He, citado pela  agência de notícias Xinhua.

"As duas partes chegaram a um consenso, não vão participar  numa guerra comercial e não vão aumentar  as respectivas taxas", adiantou o governante, que liderou a delegação chinesa que se encontrou com o secretário do Tesouro dos Estados Unidos, Steven Mnuchin, em Washington.Nos dias 17 e 18 de Maio, Washington realizou consultas entre as delegações comerciais dos EUA e da China. Os países aprovaram uma declaração na qual prometeram adoptar medidas efectivas para reduzir o défice no comércio com a China e aumentar significativamente as exportações de bens e serviços dos EUA para a China.
</Text>
<Autor>

</Autor></xml>
